ibm_watsonx_orchestrate/__init__.py
ibm_watsonx_orchestrate/agent_builder/__init__.py
ibm_watsonx_orchestrate/agent_builder/agents/__init__.py
ibm_watsonx_orchestrate/agent_builder/agents/agent.py
ibm_watsonx_orchestrate/agent_builder/agents/assistant_agent.py
ibm_watsonx_orchestrate/agent_builder/agents/custom_agent.py
ibm_watsonx_orchestrate/agent_builder/agents/external_agent.py
ibm_watsonx_orchestrate/agent_builder/agents/types.py
ibm_watsonx_orchestrate/agent_builder/agents/plugins/__init__.py
ibm_watsonx_orchestrate/agent_builder/agents/plugins/plugins.py
ibm_watsonx_orchestrate/agent_builder/agents/webchat_customizations/__init__.py
ibm_watsonx_orchestrate/agent_builder/agents/webchat_customizations/prompts.py
ibm_watsonx_orchestrate/agent_builder/agents/webchat_customizations/welcome_content.py
ibm_watsonx_orchestrate/agent_builder/channels/__init__.py
ibm_watsonx_orchestrate/agent_builder/channels/channel.py
ibm_watsonx_orchestrate/agent_builder/channels/types.py
ibm_watsonx_orchestrate/agent_builder/connections/__init__.py
ibm_watsonx_orchestrate/agent_builder/connections/connections.py
ibm_watsonx_orchestrate/agent_builder/connections/types.py
ibm_watsonx_orchestrate/agent_builder/knowledge_bases/knowledge_base.py
ibm_watsonx_orchestrate/agent_builder/knowledge_bases/knowledge_base_requests.py
ibm_watsonx_orchestrate/agent_builder/knowledge_bases/types.py
ibm_watsonx_orchestrate/agent_builder/model_policies/__init__.py
ibm_watsonx_orchestrate/agent_builder/model_policies/types.py
ibm_watsonx_orchestrate/agent_builder/models/__init__.py
ibm_watsonx_orchestrate/agent_builder/models/types.py
ibm_watsonx_orchestrate/agent_builder/phone/__init__.py
ibm_watsonx_orchestrate/agent_builder/phone/phone.py
ibm_watsonx_orchestrate/agent_builder/phone/types.py
ibm_watsonx_orchestrate/agent_builder/toolkits/base_toolkit.py
ibm_watsonx_orchestrate/agent_builder/toolkits/types.py
ibm_watsonx_orchestrate/agent_builder/tools/__init__.py
ibm_watsonx_orchestrate-2.3.0.dist-info/METADATA
ibm_watsonx_orchestrate-2.3.0.dist-info/WHEEL
ibm_watsonx_orchestrate-2.3.0.dist-info/entry_points.txt
ibm_watsonx_orchestrate-2.3.0.dist-info/licenses/LICENSE
ibm_watsonx_orchestrate-2.3.0.dist-info/RECORD
